{
  "counts": {
    "already_applied_count": 0,
    "candidate_count": 0,
    "failed_count": 0,
    "forbidden_effect_count": 0,
    "ready_to_apply_count": 0
  },
  "interaction": {
    "approaches_real_order": false,
    "calls_exchange_write": false,
    "calls_finalgate": false,
    "calls_operation_layer": false,
    "level": "L0_local_l2_tier_policy_review",
    "mutates_remote_files": false,
    "places_order": false,
    "remote_interaction_count": 0
  },
  "owner_state": "waiting_for_opportunity",
  "review_outcome_state": {
    "default_next_step": "continue_signal_coverage_monitoring",
    "groups_already_l2": [],
    "groups_ready_to_apply_l2": [],
    "l4_scope_change_recommended": false,
    "primary_judgment_source": false,
    "primary_judgment_source_name": "strategy_asset_state",
    "real_order_scope_change_recommended": false,
    "review_scope": "l2_tier_policy_review",
    "shadow_candidate_creation_recommended_now": false,
    "source_role": "l2_tier_policy_review_provenance",
    "state_family": "Review Outcome State",
    "target_mode": "shadow_candidate",
    "target_tier": "L2",
    "tradeability_decision_source": false
  },
  "review_rows": [],
  "safety_invariants": {
    "exchange_write_called": false,
    "final_gate_called": false,
    "l4_real_order_scope_expanded": false,
    "operation_layer_called": false,
    "order_created": false,
    "order_lifecycle_called": false,
    "review_only": true,
    "runtime_started": false,
    "server_files_mutated": false,
    "server_interaction": false,
    "shadow_candidate_created": false,
    "source_forbidden_effects": [],
    "strategy_parameters_changed": false,
    "tier_policy_changed": false,
    "withdrawal_or_transfer_created": false
  },
  "scope": "strategygroup_l2_tier_policy_review",
  "source_l2_intake_status": "l2_intake_dry_run_no_candidates",
  "status": "l2_tier_policy_review_no_candidates"
}
